CHANGELOG.md
LICENSE.txt
MANIFEST.in
README.md
pyproject.toml
setup.cfg
setup.py
examples/README.md
examples/assets/diseases.csv.gz
examples/assets/emoji_embeddings.csv
examples/assets/energy.csv
examples/assets/fb_edges.csv
examples/assets/fb_nodes.csv
examples/assets/hourly_taxi_data.npz
examples/assets/nyc_taxi.csv.gz
examples/assets/penguins.png
examples/assets/spike_train.csv.gz
examples/assets/station_info.csv
examples/assets/twophoton.npz
examples/gallery/apps/bokeh/crossfilter.py
examples/gallery/apps/bokeh/game_of_life.py
examples/gallery/apps/bokeh/gapminder.py
examples/gallery/apps/bokeh/mandelbrot.py
examples/gallery/apps/bokeh/nytaxi_hover.py
examples/gallery/apps/bokeh/streaming_psutil.py
examples/gallery/apps/flask/flask_app.py
examples/gallery/apps/flask/holoviews_app.py
examples/gallery/apps/flask/templates/embed.html
examples/gallery/demos/bokeh/area_chart.ipynb
examples/gallery/demos/bokeh/autompg_histogram.ipynb
examples/gallery/demos/bokeh/autompg_violins.ipynb
examples/gallery/demos/bokeh/bachelors_degrees_by_gender.ipynb
examples/gallery/demos/bokeh/bars_economic.ipynb
examples/gallery/demos/bokeh/box_draw_roi_editor.ipynb
examples/gallery/demos/bokeh/boxplot_chart.ipynb
examples/gallery/demos/bokeh/choropleth_data_link.ipynb
examples/gallery/demos/bokeh/directed_airline_routes.ipynb
examples/gallery/demos/bokeh/dot_example.ipynb
examples/gallery/demos/bokeh/dragon_curve.ipynb
examples/gallery/demos/bokeh/dropdown_economic.ipynb
examples/gallery/demos/bokeh/emoji_tsne.ipynb
examples/gallery/demos/bokeh/energy_sankey.ipynb
examples/gallery/demos/bokeh/hextile_movie_ratings.ipynb
examples/gallery/demos/bokeh/histogram_example.ipynb
examples/gallery/demos/bokeh/image_range_tool.ipynb
examples/gallery/demos/bokeh/iris_density_grid.ipynb
examples/gallery/demos/bokeh/iris_example.ipynb
examples/gallery/demos/bokeh/iris_grouped_grid.ipynb
examples/gallery/demos/bokeh/iris_splom_example.ipynb
examples/gallery/demos/bokeh/irregular_quadmesh.ipynb
holoviews_samap.egg-info/PKG-INFO
holoviews_samap.egg-info/SOURCES.txt
holoviews_samap.egg-info/dependency_links.txt
holoviews_samap.egg-info/entry_points.txt
holoviews_samap.egg-info/requires.txt
holoviews_samap.egg-info/top_level.txt
