Metadata-Version: 2.1
Name: holoviews-samap
Version: 2.0.0
Summary: Stop plotting your data - annotate your data and let it visualize itself.
Home-page: https://www.holoviews_samap.org
Author: Jean-Luc Stevens and Philipp Rudiger
Author-email: tarashanst@gmail.com
Maintainer: PyViz Developers
Maintainer-email: developers@pyviz.org
License: BSD
Platform: Windows
Platform: Mac OS X
Platform: Linux
Classifier: License :: OSI Approved :: BSD License
Classifier: Development Status :: 5 - Production/Stable
Classifier: Programming Language :: Python :: 3.6
Classifier: Programming Language :: Python :: 3.7
Classifier: Programming Language :: Python :: 3.8
Classifier: Operating System :: OS Independent
Classifier: Intended Audience :: Science/Research
Classifier: Intended Audience :: Developers
Classifier: Natural Language :: English
Classifier: Framework :: Matplotlib
Classifier: Topic :: Scientific/Engineering
Classifier: Topic :: Software Development :: Libraries
Requires-Python: >=2.7
Provides-Extra: notebook
Provides-Extra: recommended
Provides-Extra: examples
Provides-Extra: extras
Provides-Extra: tests
Provides-Extra: unit_tests
Provides-Extra: basic_tests
Provides-Extra: nbtests
Provides-Extra: doc
Provides-Extra: build
Provides-Extra: all
License-File: LICENSE.txt
